[{"監測站":"石門","監測站(英文)":"SHIHMAN","監測值(微西弗/時)":"0.055","時間":"2015-12-07 17:55","GPS經度":"121.56","GPS緯度":"25.29"},{"監測站":"三芝","監測站(英文)":"SHANGI","監測值(微西弗/時)":"0.059","時間":"2015-12-07 17:55","GPS經度":"121.52","GPS緯度":"25.23"},{"監測站":"石崩山","監測站(英文)":"SHIHBENGSHAN","監測值(微西弗/時)":"0.068","時間":"2015-12-07 17:55","GPS經度":"121.57","GPS緯度":"25.26"},{"監測站":"茂林","監測站(英文)":"MAOLIN","監測值(微西弗/時)":"0.050","時間":"2015-12-07 17:55","GPS經度":"121.59","GPS緯度":"25.27"},{"監測站":"金山","監測站(英文)":"CHINSHAN","監測值(微西弗/時)":"0.049","時間":"2015-12-07 17:55","GPS經度":"121.64","GPS緯度":"25.22"},{"監測站":"野柳","監測站(英文)":"YEHLIU","監測值(微西弗/時)":"0.053","時間":"2015-12-07 17:55","GPS經度":"121.69","GPS緯度":"25.21"},{"監測站":"大鵬","監測站(英文)":"TAPERNG","監測值(微西弗/時)":"0.064","時間":"2015-12-07 17:55","GPS經度":"121.65","GPS緯度":"25.21"},{"監測站":"陽明山","監測站(英文)":"YANGMINSHAN","監測值(微西弗/時)":"0.058","時間":"2015-12-07 17:55","GPS經度":"121.54","GPS緯度":"25.16"},{"監測站":"大坪","監測站(英文)":"TAPING","監測值(微西弗/時)":"0.065","時間":"2015-12-07 17:55","GPS經度":"121.64","GPS緯度":"25.17"},{"監測站":"萬里","監測站(英文)":"WANLI","監測值(微西弗/時)":"0.073","時間":"2015-12-07 17:55","GPS經度":"0","GPS緯度":"0"},{"監測站":"台北","監測站(英文)":"TAIPEI","監測值(微西弗/時)":"0.056","時間":"2015-12-07 17:55","GPS經度":"121.57","GPS緯度":"25.08"},{"監測站":"宜蘭","監測站(英文)":"ILAN","監測值(微西弗/時)":"0.060","時間":"2015-12-07 17:55","GPS經度":"121.76","GPS緯度":"24.76"},{"監測站":"龍潭","監測站(英文)":"LUNGTAN","監測值(微西弗/時)":"0.053","時間":"2015-12-07 17:50","GPS經度":"121.24","GPS緯度":"24.84"},{"監測站":"台中","監測站(英文)":"TAICHUNG","監測值(微西弗/時)":"0.070","時間":"2015-12-07 17:55","GPS經度":"120.68","GPS緯度":"24.15"},{"監測站":"台東","監測站(英文)":"TAITUNG","監測值(微西弗/時)":"0.054","時間":"2015-12-07 17:55","GPS經度":"121.15","GPS緯度":"22.75"},{"監測站":"高雄","監測站(英文)":"KAOHSIUNG","監測值(微西弗/時)":"0.062","時間":"2015-12-07 17:55","GPS經度":"120.35","GPS緯度":"22.65"},{"監測站":"恆春","監測站(英文)":"HENGCHUN","監測值(微西弗/時)":"0.069","時間":"2015-12-07 17:55","GPS經度":"120.75","GPS緯度":"22"},{"監測站":"龍泉","監測站(英文)":"LUNGCHUAN","監測值(微西弗/時)":"0.057","時間":"2015-12-07 17:55","GPS經度":"120.73","GPS緯度":"21.98"},{"監測站":"大光","監測站(英文)":"TAKUANG","監測值(微西弗/時)":"0.052","時間":"2015-12-07 17:55","GPS經度":"120.74","GPS緯度":"21.95"},{"監測站":"墾丁","監測站(英文)":"KENTING","監測值(微西弗/時)":"0.057","時間":"2015-12-07 17:55","GPS經度":"120.8","GPS緯度":"21.95"},{"監測站":"後壁湖","監測站(英文)":"HOUBIHU","監測值(微西弗/時)":"0.056","時間":"2015-12-07 17:55","GPS經度":"120.74","GPS緯度":"21.94"},{"監測站":"澳底","監測站(英文)":"AODI","監測值(微西弗/時)":"0.050","時間":"2015-12-07 17:55","GPS經度":"121.92","GPS緯度":"25.05"},{"監測站":"貢寮","監測站(英文)":"GONGLIAO","監測值(微西弗/時)":"0.052","時間":"2015-12-07 17:55","GPS經度":"121.92","GPS緯度":"25.01"},{"監測站":"阿里山","監測站(英文)":"ALISHAN","監測值(微西弗/時)":"0.101","時間":"2015-12-07 17:55","GPS經度":"120.81","GPS緯度":"23.51"},{"監測站":"金門","監測站(英文)":"KINMEN","監測值(微西弗/時)":"0.078","時間":"2015-12-07 17:55","GPS經度":"118.29","GPS緯度":"24.41"},{"監測站":"蘭嶼","監測站(英文)":"LANYU","監測值(微西弗/時)":"0.045","時間":"2015-12-07 17:55","GPS經度":"121.51","GPS緯度":"22.05"},{"監測站":"台南","監測站(英文)":"TAINAN","監測值(微西弗/時)":"0.062","時間":"2015-12-07 17:55","GPS經度":"120.24","GPS緯度":"23.04"},{"監測站":"龍門","監測站(英文)":"LUNGMEN","監測值(微西弗/時)":"0.056","時間":"2015-12-07 17:55","GPS經度":"121.93","GPS緯度":"25.03"},{"監測站":"雙溪","監測站(英文)":"SHUANGSI","監測值(微西弗/時)":"0.061","時間":"2015-12-07 17:55","GPS經度":"121.86","GPS緯度":"25.04"},{"監測站":"三港","監測站(英文)":"SANGANG","監測值(微西弗/時)":"0.066","時間":"2015-12-07 17:55","GPS經度":"121.88","GPS緯度":"25.05"},{"監測站":"新竹","監測站(英文)":"HSINCHU","監測值(微西弗/時)":"0.052","時間":"2015-12-07 17:55","GPS經度":"120.99","GPS緯度":"24.78"},{"監測站":"花蓮","監測站(英文)":"HUALINE","監測值(微西弗/時)":"0.053","時間":"2015-12-07 17:55","GPS經度":"121.61","GPS緯度":"23.98"},{"監測站":"澎湖","監測站(英文)":"PENGHU","監測值(微西弗/時)":"0.050","時間":"2015-12-07 17:55","GPS經度":"119.56","GPS緯度":"23.57"},{"監測站":"馬祖","監測站(英文)":"MATZU","監測值(微西弗/時)":"0.051","時間":"2015-12-07 17:55","GPS經度":"119.92","GPS緯度":"26.17"},{"監測站":"滿州","監測站(英文)":"MANJHOU","監測值(微西弗/時)":"0.051","時間":"2015-12-07 17:55","GPS經度":"120.82","GPS緯度":"22.01"},{"監測站":"板橋","監測站(英文)":"BANCIAO","監測值(微西弗/時)":"0.068","時間":"2015-12-07 17:55","GPS經度":"121.44","GPS緯度":"25"},{"監測站":"屏東市","監測站(英文)":"PINGTONG","監測值(微西弗/時)":"0.050","時間":"2015-12-07 17:55","GPS經度":"120.49","GPS緯度":"22.69"},{"監測站":"基隆","監測站(英文)":"KEELUNG","監測值(微西弗/時)":"0.059","時間":"2015-12-07 17:55","GPS經度":"121.71","GPS緯度":"25.14"},{"監測站":"頭城","監測站(英文)":"TOUCHENG","監測值(微西弗/時)":"0.052","時間":"2015-12-07 17:55","GPS經度":"121.9","GPS緯度":"24.94"},{"監測站":"竹北","監測站(英文)":"JHUBEI","監測值(微西弗/時)":"0.051","時間":"2015-12-07 17:55","GPS經度":"121.01","GPS緯度":"24.83"},{"監測站":"苗栗","監測站(英文)":"MIAOLI","監測值(微西弗/時)":"0.042","時間":"2015-12-07 17:55","GPS經度":"120.84","GPS緯度":"24.58"},{"監測站":"南投","監測站(英文)":"NANTOU","監測值(微西弗/時)":"0.053","時間":"2015-12-07 17:55","GPS經度":"120.91","GPS緯度":"23.88"},{"監測站":"彰化","監測站(英文)":"CHANGHUA","監測值(微西弗/時)":"0.065","時間":"2015-12-07 17:55","GPS經度":"120.54","GPS緯度":"24.06"},{"監測站":"雲林","監測站(英文)":"YUNLIN","監測值(微西弗/時)":"0.058","時間":"2015-12-07 17:55","GPS經度":"120.53","GPS緯度":"23.7"},{"監測站":"嘉義","監測站(英文)":"CHIAYI","監測值(微西弗/時)":"0.046","時間":"2015-12-07 17:55","GPS經度":"120.43","GPS緯度":"23.5"}]